seals/__init__.py
seals/atari.py
seals/base_envs.py
seals/classic_control.py
seals/mujoco.py
seals/py.typed
seals/util.py
seals/diagnostics/__init__.py
seals/diagnostics/branching.py
seals/diagnostics/cliff_world.py
seals/diagnostics/early_term.py
seals/diagnostics/init_shift.py
seals/diagnostics/largest_sum.py
seals/diagnostics/noisy_obs.py
seals/diagnostics/parabola.py
seals/diagnostics/proc_goal.py
seals/diagnostics/random_trans.py
seals/diagnostics/risky_path.py
seals/diagnostics/sort.py
seals/testing/__init__.py
seals/testing/envs.py
seals-0.2.1.dist-info/LICENSE
seals-0.2.1.dist-info/METADATA
seals-0.2.1.dist-info/WHEEL
seals-0.2.1.dist-info/top_level.txt
seals-0.2.1.dist-info/RECORD
