Metadata-Version: 2.1
Name: seals
Version: 0.2.1
Summary: Suite of Environments for Algorithms that Learn Specifications
Home-page: https://github.com/HumanCompatibleAI/benchmark-environments
Author: Center for Human-Compatible AI
License: MIT
Classifier: License :: OSI Approved :: MIT License
Classifier: Programming Language :: Python
Classifier: Programming Language :: Python :: 3
Classifier: Programming Language :: Python :: 3.8
Classifier: Programming Language :: Python :: 3.9
Classifier: Programming Language :: Python :: 3.10
Classifier: Programming Language :: Python :: Implementation :: CPython
Classifier: Programming Language :: Python :: Implementation :: PyPy
Classifier: License :: OSI Approved :: MIT License
Classifier: Operating System :: OS Independent
Requires-Python: >=3.8.0
License-File: LICENSE
Requires-Dist: gymnasium
Requires-Dist: numpy
Provides-Extra: dev
Requires-Dist: ipdb; extra == "dev"
Requires-Dist: jupyter; extra == "dev"
Requires-Dist: black; extra == "dev"
Requires-Dist: coverage~=4.5.4; extra == "dev"
Requires-Dist: codecov; extra == "dev"
Requires-Dist: codespell; extra == "dev"
Requires-Dist: darglint>=1.5.6; extra == "dev"
Requires-Dist: flake8; extra == "dev"
Requires-Dist: flake8-blind-except; extra == "dev"
Requires-Dist: flake8-builtins; extra == "dev"
Requires-Dist: flake8-commas; extra == "dev"
Requires-Dist: flake8-debugger; extra == "dev"
Requires-Dist: flake8-docstrings; extra == "dev"
Requires-Dist: flake8-isort; extra == "dev"
Requires-Dist: isort; extra == "dev"
Requires-Dist: matplotlib; extra == "dev"
Requires-Dist: mypy; extra == "dev"
Requires-Dist: pydocstyle; extra == "dev"
Requires-Dist: pytest; extra == "dev"
Requires-Dist: pytest-cov; extra == "dev"
Requires-Dist: pytest-xdist; extra == "dev"
Requires-Dist: pytype; extra == "dev"
Requires-Dist: stable-baselines3>=0.9.0; extra == "dev"
Requires-Dist: setuptools_scm~=7.0.5; extra == "dev"
Requires-Dist: gymnasium[classic-control,mujoco]; extra == "dev"
Requires-Dist: opencv-python; extra == "dev"
Requires-Dist: ale-py~=0.8.1; extra == "dev"
Requires-Dist: pillow; extra == "dev"
Requires-Dist: autorom[accept-rom-license]~=0.4.2; extra == "dev"
Requires-Dist: shimmy[atari]<1.0,>=0.1.0; extra == "dev"
Requires-Dist: sphinx; extra == "dev"
Requires-Dist: sphinx-autodoc-typehints>=1.21.5; extra == "dev"
Requires-Dist: sphinx-rtd-theme; extra == "dev"
Provides-Extra: docs
Requires-Dist: sphinx; extra == "docs"
Requires-Dist: sphinx-autodoc-typehints>=1.21.5; extra == "docs"
Requires-Dist: sphinx-rtd-theme; extra == "docs"
Provides-Extra: test
Requires-Dist: black; extra == "test"
Requires-Dist: coverage~=4.5.4; extra == "test"
Requires-Dist: codecov; extra == "test"
Requires-Dist: codespell; extra == "test"
Requires-Dist: darglint>=1.5.6; extra == "test"
Requires-Dist: flake8; extra == "test"
Requires-Dist: flake8-blind-except; extra == "test"
Requires-Dist: flake8-builtins; extra == "test"
Requires-Dist: flake8-commas; extra == "test"
Requires-Dist: flake8-debugger; extra == "test"
Requires-Dist: flake8-docstrings; extra == "test"
Requires-Dist: flake8-isort; extra == "test"
Requires-Dist: isort; extra == "test"
Requires-Dist: matplotlib; extra == "test"
Requires-Dist: mypy; extra == "test"
Requires-Dist: pydocstyle; extra == "test"
Requires-Dist: pytest; extra == "test"
Requires-Dist: pytest-cov; extra == "test"
Requires-Dist: pytest-xdist; extra == "test"
Requires-Dist: pytype; extra == "test"
Requires-Dist: stable-baselines3>=0.9.0; extra == "test"
Requires-Dist: setuptools_scm~=7.0.5; extra == "test"
Requires-Dist: gymnasium[classic-control,mujoco]; extra == "test"
Requires-Dist: opencv-python; extra == "test"
Requires-Dist: ale-py~=0.8.1; extra == "test"
Requires-Dist: pillow; extra == "test"
Requires-Dist: autorom[accept-rom-license]~=0.4.2; extra == "test"
Requires-Dist: shimmy[atari]<1.0,>=0.1.0; extra == "test"
Provides-Extra: mujoco
Requires-Dist: gymnasium[mujoco]; extra == "mujoco"
Provides-Extra: atari
Requires-Dist: opencv-python; extra == "atari"
Requires-Dist: ale-py~=0.8.1; extra == "atari"
Requires-Dist: pillow; extra == "atari"
Requires-Dist: autorom[accept-rom-license]~=0.4.2; extra == "atari"
Requires-Dist: shimmy[atari]<1.0,>=0.1.0; extra == "atari"
